renegade/__init__.py
renegade/client.py
renegade/http.py
renegade/types.py
renegade_sdk-0.1.9.dist-info/METADATA
renegade_sdk-0.1.9.dist-info/WHEEL
renegade_sdk-0.1.9.dist-info/licenses/LICENSE
renegade_sdk-0.1.9.dist-info/RECORD
