Metadata-Version: 2.4
Name: renegade-sdk
Version: 0.1.9
Summary: Python SDK for Renegade darkpool
Project-URL: Homepage, https://renegade.fi/
Project-URL: Repository, https://github.com/renegade-fi/python-sdk
Author-email: Renegade <joey@renegade.fi>
License-Expression: Apache-2.0
License-File: LICENSE
Keywords: arbitrum,blockchain,darkpool,defi,mpc,zero-knowledge
Classifier: Development Status :: 4 - Beta
Classifier: Intended Audience :: Developers
Classifier: License :: OSI Approved :: Apache Software License
Classifier: Programming Language :: Python :: 3
Classifier: Programming Language :: Python :: 3.13
Classifier: Topic :: Software Development :: Libraries :: Python Modules
Requires-Python: >=3.13
Requires-Dist: cryptography>=42.0.2
Requires-Dist: deprecated>=1.2.18
Requires-Dist: httpx>=0.27.0
Requires-Dist: pydantic>=2.6.1
Requires-Dist: python-dotenv>=1.0.1
Requires-Dist: web3>=6.15.1
